fgfw/__init__.py
fgfw/core.py
fgfw/data.py
fgfw/bin/libexec
fgfw/bin/libexec_linux
fgfw-0.0.4.dist-info/METADATA
fgfw-0.0.4.dist-info/WHEEL
fgfw-0.0.4.dist-info/entry_points.txt
fgfw-0.0.4.dist-info/top_level.txt
fgfw-0.0.4.dist-info/RECORD
