Metadata-Version: 2.1
Name: fgfw
Version: 0.0.4
Summary: Fuck GFW
Home-page: https://github.com/private_repo/codefast
Author: slipper
Author-email: r2fscg@gmail.com
License: UNKNOWN
Platform: UNKNOWN
Classifier: Programming Language :: Python :: 3
Classifier: License :: OSI Approved :: MIT License
Classifier: Operating System :: OS Independent
Requires-Dist: requests
Requires-Dist: codefast
